MANIFEST.in
README.rst
setup.py
collective/__init__.py
collective.taxonomysupport.egg-info/PKG-INFO
collective.taxonomysupport.egg-info/SOURCES.txt
collective.taxonomysupport.egg-info/dependency_links.txt
collective.taxonomysupport.egg-info/entry_points.txt
collective.taxonomysupport.egg-info/namespace_packages.txt
collective.taxonomysupport.egg-info/not-zip-safe
collective.taxonomysupport.egg-info/requires.txt
collective.taxonomysupport.egg-info/top_level.txt
collective/taxonomysupport/README.txt
collective/taxonomysupport/__init__.py
collective/taxonomysupport/allareas.py
collective/taxonomysupport/config.py
collective/taxonomysupport/configure.zcml
collective/taxonomysupport/extender.py
collective/taxonomysupport/i18n.sh
collective/taxonomysupport/monkey.py
collective/taxonomysupport/setuphandlers.py
collective/taxonomysupport/browser/__init__.py
collective/taxonomysupport/browser/configure.zcml
collective/taxonomysupport/browser/fix_metadata.pt
collective/taxonomysupport/browser/fix_metadata.py
collective/taxonomysupport/browser/fix_searchabletext.pt
collective/taxonomysupport/browser/fix_searchabletext.py
collective/taxonomysupport/browser/taxonomy_utils.py
collective/taxonomysupport/browser/images/add_taxonomy.png
collective/taxonomysupport/browser/images/folder_taxonomy.png
collective/taxonomysupport/browser/images/remove_taxonomy.png
collective/taxonomysupport/content/__init__.py
collective/taxonomysupport/content/configure.zcml
collective/taxonomysupport/content/folder_taxonomy.py
collective/taxonomysupport/interfaces/__init__.py
collective/taxonomysupport/interfaces/folder_taxonomy.py
collective/taxonomysupport/interfaces/taxonomy_layer.py
collective/taxonomysupport/locales/collective.taxonomysupport-manual.pot
collective/taxonomysupport/locales/collective.taxonomysupport.pot
collective/taxonomysupport/locales/runi18ndude.sh
collective/taxonomysupport/locales/it/LC_MESSAGES/collective.taxonomysupport.mo
collective/taxonomysupport/locales/it/LC_MESSAGES/collective.taxonomysupport.po
collective/taxonomysupport/profiles/default/actionicons.xml
collective/taxonomysupport/profiles/default/actions.xml
collective/taxonomysupport/profiles/default/browserlayer.xml
collective/taxonomysupport/profiles/default/catalog.xml
collective/taxonomysupport/profiles/default/collective.taxonomysupport_various.txt
collective/taxonomysupport/profiles/default/factorytool.xml
