Metadata-Version: 1.1
Name: collective.taxonomysupport
Version: 1.4.1
Summary: Add support for taxonomies to Plone contents as a news tag-like field
Home-page: https://github.com/PloneGov-IT/collective.taxonomysupport
Author: RedTurtle Technology
Author-email: sviluppoplone@redturtle.it
License: GPL
Keywords: plone plonegov taxonomy
Platform: UNKNOWN
Classifier: Development Status :: 4 - Beta
Classifier: Framework :: Plone
Classifier: Framework :: Plone :: 3.3
Classifier: Framework :: Plone :: 4.0
Classifier: Framework :: Plone :: 4.1
Classifier: Framework :: Plone :: 4.2
Classifier: Topic :: Software Development :: Libraries :: Python Modules
Classifier: License :: OSI Approved :: GNU General Public License (GPL)
